Metadata-Version: 2.1
Name: odoo13-addon-product-dimension
Version: 13.0.1.0.2
Summary: Product Dimension
Home-page: https://github.com/OCA/product-attribute
Author: brain-tec AG, ADHOC SA, Camptocamp SA, Odoo Community Association (OCA)
Author-email: support@odoo-community.org
License: AGPL-3
Platform: UNKNOWN
Classifier: Programming Language :: Python
Classifier: Framework :: Odoo
Classifier: Framework :: Odoo :: 13.0
Classifier: License :: OSI Approved :: GNU Affero General Public License v3
Classifier: Development Status :: 5 - Production/Stable
Requires-Python: >=3.5
Requires-Dist: odoo (<13.1dev,>=13.0a)
